autophylo/__init__.py
autophylo/autophylo.py
autophylo/label.py
autophylo/plot.py
autophylo/tree_builder.py
autophylo/cli/__init__.py
autophylo-1.0.4.data/data/autophylo/autophylo.conf
autophylo-1.0.4.dist-info/LICENSE.txt
autophylo-1.0.4.dist-info/METADATA
autophylo-1.0.4.dist-info/WHEEL
autophylo-1.0.4.dist-info/entry_points.txt
autophylo-1.0.4.dist-info/top_level.txt
autophylo-1.0.4.dist-info/RECORD
