Metadata-Version: 2.1
Name: autophylo
Version: 1.0.4
Summary: Autophylo is used to generate phylogentic trees automatically.
Author-email: "Amogelang R. Raphenya" <raphenar@mcmaster.ca>
Maintainer-email: "Amogelang R. Raphenya" <raphenar@mcmaster.ca>
License: Copyright (c) 2024 Amogelang R. Raphenya (raphenar@mcmaster.ca)
Project-URL: Homepage, https://github.com/raphenya/autophylo
Project-URL: Issues, https://github.com/raphenya/autophylo/issues
Keywords: phylogentic,autophy,automatic,autophylo
Classifier: Programming Language :: Python :: 3
Classifier: Operating System :: OS Independent
Requires-Python: >=3.8
License-File: LICENSE.txt
Requires-Dist: joblib
Requires-Dist: biopython
